<?xml version="1.0" encoding="UTF-8"?>
<plugins>

	<plugin>
		<name>JuSt an Easter Egg</name>
		<version>0.1</version>
		<contributor>Petky Péter</contributor>
		<learnmore>https://servicedesk-marketplace.com/</learnmore>
		<description>This is a test plug-in for market testing</description>
		<link>http://libuzhnu.brinkster.net/market/RT-Extension-Jse.tar.gz</link>
	</plugin>
	<plugin>
		<name>AttachmentsColored</name>
		<version>0.1</version>
		<contributor>Tóth Lajos</contributor>
		<learnmore>https://servicedesk-marketplace.com/</learnmore>
		<description>This is a test plug-in for market testing</description>
		<link>http://libuzhnu.brinkster.net/market/RT-Extension-AttachmentsColored.tar.gz</link>
	</plugin>
	<plugin>
		<name>CRMfolderQuickCreate</name>
		<version>0.1</version>
		<contributor>Tóth Lajos</contributor>
		<learnmore>https://servicedesk-marketplace.com/</learnmore>
		<description>This is a test plug-in for market testing</description>
		<link>RT-Extension-CRMfolderQuickCreate.zip</link>
	</plugin>
	<plugin>
		<name>QuickSearch</name>
		<version>0.1</version>
		<contributor>Tóth Lajos</contributor>
		<learnmore>https://servicedesk-marketplace.com/</learnmore>
		<description>This is a test plug-in for market testing</description>
		<link>http://libuzhnu.brinkster.net/market/RT-Extension-QuickSearch.tar.gz</link>
	</plugin>
	<plugin>
		<name>UserList</name>
		<version>0.1</version>
		<contributor>Tóth Lajos</contributor>
		<learnmore>https://servicedesk-marketplace.com/</learnmore>
		<description>This is a test plug-in for market testing</description>
		<link>http://libuzhnu.brinkster.net/market/RT-Extension-UserList.tar.gz</link>
	</plugin>
	<plugin>
		<name>QuickChild </name>
		<version>0.1</version>
		<contributor>Tóth Lajos</contributor>
		<learnmore>https://servicedesk-marketplace.com/</learnmore>
		<description>This is a test plug-in for market testing</description>
		<link>http://libuzhnu.brinkster.net/market/RT-Extension-QuickChild.tar.gz</link>
	</plugin>
	<plugin>
		<name>BigBox</name>
		<version>0.1</version>
		<contributor>Tóth Lajos</contributor>
		<learnmore>https://servicedesk-marketplace.com/</learnmore>
		<description>This is a test plug-in for market testing</description>
		<link>http://libuzhnu.brinkster.net/market/RT-Extension-BigBox.tar.gz</link>
	</plugin>
	<plugin>
		<name>RawExport</name>
		<version>0.1</version>
		<contributor>Tóth Lajos</contributor>
		<learnmore>https://servicedesk-marketplace.com/</learnmore>
		<description>This is a test plug-in for market testing</description>
		<link>http://libuzhnu.brinkster.net/market/RT-Extension-RawExport.tar.gz</link>
	</plugin>
	<plugin>
		<name>rt-extension-rest2</name>
		<version>1.07</version>
		<contributor>cbrandtbuffalo</contributor>
		<learnmore>https://servicedesk-marketplace.com/</learnmore>
		<description>This is a test plug-in for market testing</description>
		<link>https://github.com/bestpractical/rt-extension-rest2/archive/master.zip</link>
	</plugin>
	<plugin>
		<name>JSGantt</name>
		<version>1.04</version>
		<contributor>Best Practical Solutions</contributor>
		<learnmore>https://metacpan.org/pod/RT::Extension::JSGantt</learnmore>
		<description>This extension uses the Starts and Due dates, along with ticket dependencies, to produce Gantt charts.</description>
		<link>https://cpan.metacpan.org/authors/id/B/BP/BPS/RT-Extension-JSGantt.tar.gz</link>
	</plugin>
	<plugin>
		<name>Gravatar</name>
		<version>2.01</version>
		<contributor>Christian Loos</contributor>
		<learnmore>https://metacpan.org/pod/RT::Extension::Gravatar</learnmore>
		<description>This Plugin displays Gravatar image on the following pages: More about the requestors widget. Modify user page. About me (Preferences). User Summary</description>
		<link>https://cpan.metacpan.org/authors/id/C/CL/CLOOS/RT-Extension-Gravatar.tar.gz</link>
	</plugin>
	<plugin>
		<name>REST2</name>
		<version>1.07</version>
		<contributor>Best Practical Solutions</contributor>
		<learnmore>https://metacpan.org/pod/RT::Extension::REST2</learnmore>
		<description>RT::Extension::REST2 - Adds a modern REST API to RT under /REST/2.0/</description>
		<link>https://cpan.metacpan.org/authors/id/B/BP/BPS/RT-Extension-REST2.tar.gz</link>
	</plugin>
	<plugin>
		<name>Macro recorder</name>
		<version>0.1 RC1</version>
		<contributor>Péter Petky</contributor>
		<learnmore>https://servicedesk-marketplace.com/</learnmore>
		<description>This is a test plug-in for market testing</description>
		<link>RT-Extension-macrorecorder.zip</link>
	</plugin>
</plugins>
